{
  "$schema": "https://json.schemastore.org/tsconfig",
  "compilerOptions": {
    "allowJs": true,
    "composite": false,
    "esModuleInterop": true,
    "forceConsistentCasingInFileNames": true,
    "inlineSources": false,
    "isolatedModules": true,
    "module": "ESNext",
    "moduleResolution": "Node",
    "noEmit": true,
    "noUnusedLocals": false,
    "noUnusedParameters": false,
    "preserveWatchOutput": true,
    "resolveJsonModule": true,
    "skipLibCheck": true,
    "strict": true,
    "target": "ESNext"
  },
  "display": "Base",
  "exclude": ["node_modules"]
}
